lila/.env
lila/__init__.py
lila/main.py
lila/app/__init__.py
lila/app/config.py
lila/app/connections.py
lila/app/helpers/helpers.py
lila/app/locales/changelogs.json
lila/app/locales/translations.json
lila/app/middlewares/defaults.py
lila/app/middlewares/middlewares.py
lila/app/models/user.py
lila/app/routes/admin.py
lila/app/routes/api.py
lila/app/routes/routes.py
lila/app/security/blocked_ips.json
lila/app/security/blocked_urls.json
lila/app/security/sensitive_paths.json
lila/cli/auth.py
lila/cli/create_admin.py
lila/cli/create_panel_admin.py
lila/cli/migrations.py
lila/cli/minify.py
lila/cli/model.py
lila/cli/prerender.py
lila/cli/react.py
lila/cli/scaffold.py
lila/cli/scaffold_crud.py
lila/cli/auth/models/auth.py
lila/cli/auth/models/user.py
lila/cli/auth/routes/auth.py
lila/cli/auth/routes/authenticated.py
lila/cli/auth/templates/change-password.html
lila/cli/auth/templates/dashboard.html
lila/cli/auth/templates/forgot-password.html
lila/cli/auth/templates/invalid-token.html
lila/cli/auth/templates/login.html
lila/cli/auth/templates/profile.html
lila/cli/auth/templates/register.html
lila/core/__init__.py
lila/core/admin.py
lila/core/app.py
lila/core/background.py
lila/core/controller.py
lila/core/database.py
lila/core/logger.py
lila/core/middleware.py
lila/core/request.py
lila/core/responses.py
lila/core/routing.py
lila/core/session.py
lila/core/templates.py
lila/core/translate.py
lila/public/robots.txt
lila/public/css/lila.css
lila/public/img/lila.png
lila/public/js/utils.js
lila/public/swagger/swagger-ui-bundle.js
lila/public/swagger/swagger-ui-standalone-preset.js
lila/public/swagger/swagger-ui.css
lila/templates/html/404.html
lila/templates/html/index.html
lila/templates/html/admin/dashboard.html
lila/templates/html/admin/login.html
lila/templates/html/admin/model_table.html
lila/templates/markdown/changelogs.md
lila/templates/markdown/example.md
lila/templates/markdown/layout.html
lila_framework-0.9.1.dist-info/licenses/LICENSE
lila_framework-0.9.1.dist-info/METADATA
lila_framework-0.9.1.dist-info/WHEEL
lila_framework-0.9.1.dist-info/entry_points.txt
lila_framework-0.9.1.dist-info/top_level.txt
lila_framework-0.9.1.dist-info/RECORD
