Metadata-Version: 2.4
Name: lila-framework
Version: 0.9.1
Summary: Framework web Python
Author-email: Andrés Paiva Silveira <andrespaivasilveiraa@gmail.com>
Project-URL: Homepage, https://seip25.github.io/Lila/
Project-URL: Repository, https://github.com/seip25/Lila
Classifier: Development Status :: 4 - Beta
Classifier: Intended Audience :: Developers
Classifier: Topic :: Software Development :: Libraries :: Application Frameworks
Classifier: License :: OSI Approved :: MIT License
Classifier: Programming Language :: Python :: 3.9
Classifier: Programming Language :: Python :: 3.10
Classifier: Programming Language :: Python :: 3.11
Classifier: Programming Language :: Python :: 3.12
Classifier: Programming Language :: Python :: 3.13
Classifier: Operating System :: OS Independent
Requires-Python: >=3.9
License-File: LICENSE
Requires-Dist: starlette==0.48.0
Requires-Dist: jinja2==3.1.6
Requires-Dist: uvicorn==0.37.0
Requires-Dist: pydantic==2.11.9
Requires-Dist: pydantic[email]
Requires-Dist: python-dotenv==1.1.1
Requires-Dist: itsdangerous==2.2.0
Requires-Dist: mysql-connector-python==9.4.0
Requires-Dist: argon2-cffi==25.1.0
Requires-Dist: markdown==3.9
Requires-Dist: SQLAlchemy==2.0.43
Requires-Dist: PyJWT==2.10.1
Requires-Dist: psutil==7.1.0
Requires-Dist: python-multipart==0.0.20
Requires-Dist: typer==0.19.2
Requires-Dist: pillow==11.3.0
Requires-Dist: rjsmin==1.2.4
Requires-Dist: rcssmin==1.2.1
Requires-Dist: jinja2-htmlmin==1.0.1
Requires-Dist: starlette-compress==1.6.1
Requires-Dist: psycopg==3.2.10
Dynamic: license-file
